dd_lib_i18n_base/__init__.py
dd_lib_i18n_base/exceptions.py
dd_lib_i18n_base/i18n.py
dd_lib_i18n_base/internal.py
dd_lib_i18n_base/message.py
dd_lib_i18n_base/py.typed
dd_lib_i18n_base-1.4.0.dist-info/METADATA
dd_lib_i18n_base-1.4.0.dist-info/WHEEL
dd_lib_i18n_base-1.4.0.dist-info/RECORD
